zmdm_mcp_swagger/__init__.py
zmdm_mcp_swagger/config_generator.py
zmdm_mcp_swagger/file_utils.py
zmdm_mcp_swagger/request.py
zmdm_mcp_swagger/swagger_helper.py
zmdm_mcp_swagger/typescript_generator.py
zmdm_mcp_swagger-0.3.1.dist-info/METADATA
zmdm_mcp_swagger-0.3.1.dist-info/WHEEL
zmdm_mcp_swagger-0.3.1.dist-info/entry_points.txt
zmdm_mcp_swagger-0.3.1.dist-info/RECORD
