Metadata-Version: 2.4
Name: zmdm-mcp-swagger
Version: 0.3.1
Summary: Add your description here
Author-email: xiaojy <735516422@qq.com>
Requires-Python: >=3.13
Requires-Dist: mcp[cli]>=1.10.1
Requires-Dist: requests>=2.31.0
